{
  "Game": {
    "DateTime": "2022-05-24T17:14:59.9606981+00:00",
    "EnemyId": "1",
    "MapName": "Blackburn AIE",
    "EnemySelectedRace": 3,
    "EnemyRace": 3,
    "MySelectedRace": 3,
    "MyRace": 3,
    "Length": 28080,
    "Result": 1,
    "EnemyStrategies": {},
    "Builds": {
      "0": "OneBaseCarriers"
    },
    "EnemyChat": {},
    "MyChat": {}
  },
  "MLFramesData": {
    "0": {
      "BuildHistory": {
        "0": "OneBaseCarriers"
      },
      "EnemyStrategyHistory": {},
      "ActiveEnemyStrategies": [],
      "DetectedEnemyStrategies": [],
      "SelfUnitCounts": {
        "PROTOSS_PROBE": 12,
        "PROTOSS_NEXUS": 1
      },
      "EnemyUnitCounts": {},
      "SelfBaseData": {
        "BaseCount": 1,
        "WorkerCount": 12,
        "OpenGeyserCount": 2,
        "BuiltGeyserCount": 0,
        "MinedGas": 0,
        "MineralPatchCount": 8,
        "MinedMinerals": 0
      },
      "EnemyBaseData": {
        "BaseCount": 0,
        "WorkerCount": 0,
        "OpenGeyserCount": 0,
        "BuiltGeyserCount": 0,
        "MinedGas": 0,
        "MineralPatchCount": 0,
        "MinedMinerals": 0
      }
    },
    "1344": {
      "BuildHistory": {
        "0": "OneBaseCarriers"
      },
      "EnemyStrategyHistory": {},
      "ActiveEnemyStrategies": [],
      "DetectedEnemyStrategies": [],
      "SelfUnitCounts": {
        "PROTOSS_PROBE": 16,
        "PROTOSS_PYLON": 1,
        "PROTOSS_GATEWAY": 1,
        "PROTOSS_NEXUS": 1,
        "PROTOSS_ASSIMILATOR": 2
      },
      "EnemyUnitCounts": {},
      "SelfBaseData": {
        "BaseCount": 1,
        "WorkerCount": 16,
        "OpenGeyserCount": 2,
        "BuiltGeyserCount": 0,
        "MinedGas": 0,
        "MineralPatchCount": 8,
        "MinedMinerals": 775
      },
      "EnemyBaseData": {
        "BaseCount": 0,
        "WorkerCount": 0,
        "OpenGeyserCount": 0,
        "BuiltGeyserCount": 0,
        "MinedGas": 0,
        "MineralPatchCount": 0,
        "MinedMinerals": 0
      }
    },
    "2688": {
      "BuildHistory": {
        "0": "OneBaseCarriers"
      },
      "EnemyStrategyHistory": {},
      "ActiveEnemyStrategies": [],
      "DetectedEnemyStrategies": [],
      "SelfUnitCounts": {
        "PROTOSS_PROBE": 21,
        "PROTOSS_GATEWAY": 1,
        "PROTOSS_ASSIMILATOR": 2,
        "PROTOSS_NEXUS": 1,
        "PROTOSS_CYBERNETICSCORE": 1,
        "PROTOSS_PYLON": 2,
        "PROTOSS_FORGE": 1
      },
      "EnemyUnitCounts": {
        "PROTOSS_PROBE": 1
      },
      "SelfBaseData": {
        "BaseCount": 1,
        "WorkerCount": 21,
        "OpenGeyserCount": 2,
        "BuiltGeyserCount": 0,
        "MinedGas": 0,
        "MineralPatchCount": 8,
        "MinedMinerals": 1480
      },
      "EnemyBaseData": {
        "BaseCount": 0,
        "WorkerCount": 1,
        "OpenGeyserCount": 0,
        "BuiltGeyserCount": 0,
        "MinedGas": 0,
        "MineralPatchCount": 0,
        "MinedMinerals": 0
      }
    },
    "4032": {
      "BuildHistory": {
        "0": "OneBaseCarriers"
      },
      "EnemyStrategyHistory": {},
      "ActiveEnemyStrategies": [],
      "DetectedEnemyStrategies": [],
      "SelfUnitCounts": {
        "PROTOSS_PROBE": 23,
        "PROTOSS_GATEWAY": 1,
        "PROTOSS_PHOTONCANNON": 1,
        "PROTOSS_ASSIMILATOR": 2,
        "PROTOSS_NEXUS": 1,
        "PROTOSS_SHIELDBATTERY": 1,
        "PROTOSS_STARGATE": 1,
        "PROTOSS_SENTRY": 1,
        "PROTOSS_PYLON": 3,
        "PROTOSS_CYBERNETICSCORE": 1,
        "PROTOSS_FORGE": 1
      },
      "EnemyUnitCounts": {},
      "SelfBaseData": {
        "BaseCount": 1,
        "WorkerCount": 23,
        "OpenGeyserCount": 2,
        "BuiltGeyserCount": 0,
        "MinedGas": 0,
        "MineralPatchCount": 8,
        "MinedMinerals": 2345
      },
      "EnemyBaseData": {
        "BaseCount": 0,
        "WorkerCount": 0,
        "OpenGeyserCount": 0,
        "BuiltGeyserCount": 0,
        "MinedGas": 0,
        "MineralPatchCount": 0,
        "MinedMinerals": 0
      }
    },
    "5376": {
      "BuildHistory": {
        "0": "OneBaseCarriers"
      },
      "EnemyStrategyHistory": {},
      "ActiveEnemyStrategies": [],
      "DetectedEnemyStrategies": [],
      "SelfUnitCounts": {
        "PROTOSS_PROBE": 23,
        "PROTOSS_ASSIMILATOR": 2,
        "PROTOSS_PYLON": 5,
        "PROTOSS_GATEWAY": 1,
        "PROTOSS_FLEETBEACON": 1,
        "PROTOSS_STARGATE": 1,
        "PROTOSS_PHOTONCANNON": 2,
        "PROTOSS_SHIELDBATTERY": 2,
        "PROTOSS_SENTRY": 1,
        "PROTOSS_FORGE": 1,
        "PROTOSS_CYBERNETICSCORE": 1,
        "PROTOSS_ORACLE": 1,
        "PROTOSS_NEXUS": 1
      },
      "EnemyUnitCounts": {},
      "SelfBaseData": {
        "BaseCount": 1,
        "WorkerCount": 23,
        "OpenGeyserCount": 2,
        "BuiltGeyserCount": 0,
        "MinedGas": 0,
        "MineralPatchCount": 8,
        "MinedMinerals": 3290
      },
      "EnemyBaseData": {
        "BaseCount": 0,
        "WorkerCount": 0,
        "OpenGeyserCount": 0,
        "BuiltGeyserCount": 0,
        "MinedGas": 0,
        "MineralPatchCount": 0,
        "MinedMinerals": 0
      }
    },
    "6720": {
      "BuildHistory": {
        "0": "OneBaseCarriers"
      },
      "EnemyStrategyHistory": {},
      "ActiveEnemyStrategies": [],
      "DetectedEnemyStrategies": [],
      "SelfUnitCounts": {
        "PROTOSS_PROBE": 23,
        "PROTOSS_CARRIER": 1,
        "PROTOSS_ASSIMILATOR": 2,
        "PROTOSS_PYLON": 5,
        "PROTOSS_SHIELDBATTERY": 4,
        "PROTOSS_GATEWAY": 1,
        "PROTOSS_FLEETBEACON": 1,
        "PROTOSS_STARGATE": 1,
        "PROTOSS_PHOTONCANNON": 3,
        "PROTOSS_SENTRY": 1,
        "PROTOSS_FORGE": 1,
        "PROTOSS_CYBERNETICSCORE": 1,
        "PROTOSS_ORACLE": 1,
        "PROTOSS_NEXUS": 1
      },
      "EnemyUnitCounts": {
        "PROTOSS_PROBE": 7,
        "PROTOSS_CYBERNETICSCORE": 1,
        "PROTOSS_STARGATE": 3,
        "PROTOSS_ASSIMILATOR": 2,
        "PROTOSS_GATEWAY": 1,
        "PROTOSS_NEXUS": 1,
        "PROTOSS_PYLON": 4
      },
      "SelfBaseData": {
        "BaseCount": 1,
        "WorkerCount": 23,
        "OpenGeyserCount": 2,
        "BuiltGeyserCount": 0,
        "MinedGas": 0,
        "MineralPatchCount": 8,
        "MinedMinerals": 4245
      },
      "EnemyBaseData": {
        "BaseCount": 1,
        "WorkerCount": 7,
        "OpenGeyserCount": 0,
        "BuiltGeyserCount": 2,
        "MinedGas": 4500,
        "MineralPatchCount": 8,
        "MinedMinerals": 10800
      }
    },
    "8064": {
      "BuildHistory": {
        "0": "OneBaseCarriers"
      },
      "EnemyStrategyHistory": {},
      "ActiveEnemyStrategies": [],
      "DetectedEnemyStrategies": [],
      "SelfUnitCounts": {
        "PROTOSS_PROBE": 22,
        "PROTOSS_CARRIER": 2,
        "PROTOSS_ASSIMILATOR": 2,
        "PROTOSS_PYLON": 5,
        "PROTOSS_SHIELDBATTERY": 5,
        "PROTOSS_GATEWAY": 1,
        "PROTOSS_FLEETBEACON": 1,
        "PROTOSS_STARGATE": 1,
        "PROTOSS_PHOTONCANNON": 4,
        "PROTOSS_SENTRY": 1,
        "PROTOSS_FORGE": 1,
        "PROTOSS_CYBERNETICSCORE": 1,
        "PROTOSS_NEXUS": 1
      },
      "EnemyUnitCounts": {
        "PROTOSS_PROBE": 8,
        "PROTOSS_VOIDRAY": 6,
        "PROTOSS_PYLON": 6,
        "PROTOSS_CYBERNETICSCORE": 1,
        "PROTOSS_STARGATE": 3,
        "PROTOSS_GATEWAY": 1,
        "PROTOSS_ASSIMILATOR": 2,
        "PROTOSS_NEXUS": 1
      },
      "SelfBaseData": {
        "BaseCount": 1,
        "WorkerCount": 22,
        "OpenGeyserCount": 2,
        "BuiltGeyserCount": 0,
        "MinedGas": 0,
        "MineralPatchCount": 8,
        "MinedMinerals": 5205
      },
      "EnemyBaseData": {
        "BaseCount": 1,
        "WorkerCount": 8,
        "OpenGeyserCount": 0,
        "BuiltGeyserCount": 2,
        "MinedGas": 4500,
        "MineralPatchCount": 8,
        "MinedMinerals": 10800
      }
    },
    "9408": {
      "BuildHistory": {
        "0": "OneBaseCarriers"
      },
      "EnemyStrategyHistory": {},
      "ActiveEnemyStrategies": [],
      "DetectedEnemyStrategies": [],
      "SelfUnitCounts": {
        "PROTOSS_PYLON": 5,
        "PROTOSS_ASSIMILATOR": 2,
        "PROTOSS_PROBE": 22,
        "PROTOSS_INTERCEPTOR": 14,
        "PROTOSS_STARGATE": 1,
        "PROTOSS_CYBERNETICSCORE": 1,
        "PROTOSS_CARRIER": 2,
        "PROTOSS_PHOTONCANNON": 3,
        "PROTOSS_SHIELDBATTERY": 5,
        "PROTOSS_GATEWAY": 1,
        "PROTOSS_SENTRY": 1,
        "PROTOSS_NEXUS": 1,
        "PROTOSS_FLEETBEACON": 1,
        "PROTOSS_FORGE": 1
      },
      "EnemyUnitCounts": {
        "PROTOSS_PROBE": 8,
        "PROTOSS_VOIDRAY": 6,
        "PROTOSS_PYLON": 6,
        "PROTOSS_CYBERNETICSCORE": 1,
        "PROTOSS_ORACLE": 1,
        "PROTOSS_STARGATE": 3,
        "PROTOSS_GATEWAY": 1,
        "PROTOSS_ASSIMILATOR": 2,
        "PROTOSS_NEXUS": 1
      },
      "SelfBaseData": {
        "BaseCount": 1,
        "WorkerCount": 22,
        "OpenGeyserCount": 2,
        "BuiltGeyserCount": 0,
        "MinedGas": 0,
        "MineralPatchCount": 8,
        "MinedMinerals": 6085
      },
      "EnemyBaseData": {
        "BaseCount": 1,
        "WorkerCount": 8,
        "OpenGeyserCount": 0,
        "BuiltGeyserCount": 2,
        "MinedGas": 4500,
        "MineralPatchCount": 8,
        "MinedMinerals": 10800
      }
    },
    "10752": {
      "BuildHistory": {
        "0": "OneBaseCarriers"
      },
      "EnemyStrategyHistory": {},
      "ActiveEnemyStrategies": [],
      "DetectedEnemyStrategies": [],
      "SelfUnitCounts": {
        "PROTOSS_PYLON": 5,
        "PROTOSS_ASSIMILATOR": 2,
        "PROTOSS_PROBE": 22,
        "PROTOSS_STARGATE": 1,
        "PROTOSS_CYBERNETICSCORE": 1,
        "PROTOSS_CARRIER": 2,
        "PROTOSS_PHOTONCANNON": 3,
        "PROTOSS_SHIELDBATTERY": 5,
        "PROTOSS_GATEWAY": 1,
        "PROTOSS_SENTRY": 1,
        "PROTOSS_NEXUS": 1,
        "PROTOSS_FLEETBEACON": 1,
        "PROTOSS_FORGE": 1
      },
      "EnemyUnitCounts": {
        "PROTOSS_PROBE": 8,
        "PROTOSS_VOIDRAY": 8,
        "PROTOSS_PYLON": 6,
        "PROTOSS_CYBERNETICSCORE": 1,
        "PROTOSS_ORACLE": 1,
        "PROTOSS_STARGATE": 3,
        "PROTOSS_GATEWAY": 1,
        "PROTOSS_ASSIMILATOR": 2,
        "PROTOSS_NEXUS": 1
      },
      "SelfBaseData": {
        "BaseCount": 1,
        "WorkerCount": 22,
        "OpenGeyserCount": 2,
        "BuiltGeyserCount": 0,
        "MinedGas": 0,
        "MineralPatchCount": 7,
        "MinedMinerals": 7030
      },
      "EnemyBaseData": {
        "BaseCount": 1,
        "WorkerCount": 8,
        "OpenGeyserCount": 0,
        "BuiltGeyserCount": 2,
        "MinedGas": 4500,
        "MineralPatchCount": 8,
        "MinedMinerals": 10800
      }
    },
    "12096": {
      "BuildHistory": {
        "0": "OneBaseCarriers"
      },
      "EnemyStrategyHistory": {},
      "ActiveEnemyStrategies": [],
      "DetectedEnemyStrategies": [],
      "SelfUnitCounts": {
        "PROTOSS_PYLON": 5,
        "PROTOSS_ASSIMILATOR": 2,
        "PROTOSS_PROBE": 22,
        "PROTOSS_INTERCEPTOR": 12,
        "PROTOSS_STARGATE": 1,
        "PROTOSS_CYBERNETICSCORE": 1,
        "PROTOSS_CARRIER": 2,
        "PROTOSS_PHOTONCANNON": 4,
        "PROTOSS_SHIELDBATTERY": 5,
        "PROTOSS_GATEWAY": 1,
        "PROTOSS_SENTRY": 1,
        "PROTOSS_NEXUS": 1,
        "PROTOSS_FLEETBEACON": 1,
        "PROTOSS_FORGE": 1
      },
      "EnemyUnitCounts": {
        "PROTOSS_PROBE": 8,
        "PROTOSS_VOIDRAY": 8,
        "PROTOSS_PYLON": 6,
        "PROTOSS_CYBERNETICSCORE": 1,
        "PROTOSS_STARGATE": 3,
        "PROTOSS_GATEWAY": 1,
        "PROTOSS_ASSIMILATOR": 2,
        "PROTOSS_NEXUS": 1
      },
      "SelfBaseData": {
        "BaseCount": 1,
        "WorkerCount": 22,
        "OpenGeyserCount": 2,
        "BuiltGeyserCount": 0,
        "MinedGas": 0,
        "MineralPatchCount": 5,
        "MinedMinerals": 7735
      },
      "EnemyBaseData": {
        "BaseCount": 1,
        "WorkerCount": 8,
        "OpenGeyserCount": 0,
        "BuiltGeyserCount": 2,
        "MinedGas": 4500,
        "MineralPatchCount": 8,
        "MinedMinerals": 10800
      }
    },
    "13440": {
      "BuildHistory": {
        "0": "OneBaseCarriers"
      },
      "EnemyStrategyHistory": {},
      "ActiveEnemyStrategies": [],
      "DetectedEnemyStrategies": [],
      "SelfUnitCounts": {
        "PROTOSS_PYLON": 5,
        "PROTOSS_ASSIMILATOR": 2,
        "PROTOSS_PROBE": 22,
        "PROTOSS_STARGATE": 1,
        "PROTOSS_CYBERNETICSCORE": 1,
        "PROTOSS_CARRIER": 2,
        "PROTOSS_PHOTONCANNON": 3,
        "PROTOSS_SHIELDBATTERY": 5,
        "PROTOSS_GATEWAY": 1,
        "PROTOSS_SENTRY": 1,
        "PROTOSS_NEXUS": 1,
        "PROTOSS_FLEETBEACON": 1,
        "PROTOSS_FORGE": 1
      },
      "EnemyUnitCounts": {
        "PROTOSS_PROBE": 8,
        "PROTOSS_VOIDRAY": 10,
        "PROTOSS_PYLON": 6,
        "PROTOSS_CYBERNETICSCORE": 1,
        "PROTOSS_ORACLE": 1,
        "PROTOSS_STARGATE": 3,
        "PROTOSS_GATEWAY": 1,
        "PROTOSS_ASSIMILATOR": 2,
        "PROTOSS_NEXUS": 1
      },
      "SelfBaseData": {
        "BaseCount": 1,
        "WorkerCount": 22,
        "OpenGeyserCount": 2,
        "BuiltGeyserCount": 0,
        "MinedGas": 0,
        "MineralPatchCount": 4,
        "MinedMinerals": 8245
      },
      "EnemyBaseData": {
        "BaseCount": 1,
        "WorkerCount": 8,
        "OpenGeyserCount": 0,
        "BuiltGeyserCount": 2,
        "MinedGas": 4500,
        "MineralPatchCount": 8,
        "MinedMinerals": 10800
      }
    },
    "14784": {
      "BuildHistory": {
        "0": "OneBaseCarriers"
      },
      "EnemyStrategyHistory": {},
      "ActiveEnemyStrategies": [],
      "DetectedEnemyStrategies": [],
      "SelfUnitCounts": {
        "PROTOSS_PYLON": 5,
        "PROTOSS_ASSIMILATOR": 2,
        "PROTOSS_PROBE": 22,
        "PROTOSS_STARGATE": 1,
        "PROTOSS_CYBERNETICSCORE": 1,
        "PROTOSS_CARRIER": 2,
        "PROTOSS_SHIELDBATTERY": 4,
        "PROTOSS_GATEWAY": 1,
        "PROTOSS_INTERCEPTOR": 11,
        "PROTOSS_NEXUS": 1,
        "PROTOSS_PHOTONCANNON": 2,
        "PROTOSS_FLEETBEACON": 1,
        "PROTOSS_FORGE": 1
      },
      "EnemyUnitCounts": {
        "PROTOSS_VOIDRAY": 7,
        "PROTOSS_PROBE": 8,
        "PROTOSS_PYLON": 6,
        "PROTOSS_CYBERNETICSCORE": 1,
        "PROTOSS_ORACLE": 1,
        "PROTOSS_STARGATE": 3,
        "PROTOSS_GATEWAY": 1,
        "PROTOSS_ASSIMILATOR": 2,
        "PROTOSS_NEXUS": 1
      },
      "SelfBaseData": {
        "BaseCount": 1,
        "WorkerCount": 22,
        "OpenGeyserCount": 2,
        "BuiltGeyserCount": 0,
        "MinedGas": 0,
        "MineralPatchCount": 4,
        "MinedMinerals": 8750
      },
      "EnemyBaseData": {
        "BaseCount": 1,
        "WorkerCount": 8,
        "OpenGeyserCount": 0,
        "BuiltGeyserCount": 2,
        "MinedGas": 4500,
        "MineralPatchCount": 8,
        "MinedMinerals": 10800
      }
    },
    "16128": {
      "BuildHistory": {
        "0": "OneBaseCarriers"
      },
      "EnemyStrategyHistory": {},
      "ActiveEnemyStrategies": [],
      "DetectedEnemyStrategies": [],
      "SelfUnitCounts": {
        "PROTOSS_PYLON": 5,
        "PROTOSS_ASSIMILATOR": 2,
        "PROTOSS_PROBE": 22,
        "PROTOSS_SENTRY": 1,
        "PROTOSS_STARGATE": 1,
        "PROTOSS_CYBERNETICSCORE": 1,
        "PROTOSS_INTERCEPTOR": 16,
        "PROTOSS_CARRIER": 2,
        "PROTOSS_PHOTONCANNON": 4,
        "PROTOSS_SHIELDBATTERY": 6,
        "PROTOSS_GATEWAY": 1,
        "PROTOSS_NEXUS": 1,
        "PROTOSS_FLEETBEACON": 1,
        "PROTOSS_FORGE": 1
      },
      "EnemyUnitCounts": {
        "PROTOSS_PROBE": 8,
        "PROTOSS_PYLON": 6,
        "PROTOSS_CYBERNETICSCORE": 1,
        "PROTOSS_STARGATE": 3,
        "PROTOSS_VOIDRAY": 2,
        "PROTOSS_GATEWAY": 1,
        "PROTOSS_ASSIMILATOR": 2,
        "PROTOSS_NEXUS": 1
      },
      "SelfBaseData": {
        "BaseCount": 1,
        "WorkerCount": 22,
        "OpenGeyserCount": 2,
        "BuiltGeyserCount": 0,
        "MinedGas": 0,
        "MineralPatchCount": 4,
        "MinedMinerals": 9255
      },
      "EnemyBaseData": {
        "BaseCount": 1,
        "WorkerCount": 8,
        "OpenGeyserCount": 0,
        "BuiltGeyserCount": 2,
        "MinedGas": 4500,
        "MineralPatchCount": 8,
        "MinedMinerals": 10800
      }
    },
    "17472": {
      "BuildHistory": {
        "0": "OneBaseCarriers"
      },
      "EnemyStrategyHistory": {},
      "ActiveEnemyStrategies": [],
      "DetectedEnemyStrategies": [],
      "SelfUnitCounts": {
        "PROTOSS_PYLON": 5,
        "PROTOSS_ASSIMILATOR": 2,
        "PROTOSS_PROBE": 22,
        "PROTOSS_SENTRY": 1,
        "PROTOSS_STARGATE": 1,
        "PROTOSS_CYBERNETICSCORE": 1,
        "PROTOSS_INTERCEPTOR": 16,
        "PROTOSS_CARRIER": 2,
        "PROTOSS_PHOTONCANNON": 5,
        "PROTOSS_SHIELDBATTERY": 6,
        "PROTOSS_GATEWAY": 1,
        "PROTOSS_NEXUS": 1,
        "PROTOSS_FLEETBEACON": 1,
        "PROTOSS_FORGE": 1
      },
      "EnemyUnitCounts": {
        "PROTOSS_STARGATE": 3,
        "PROTOSS_PROBE": 16,
        "PROTOSS_NEXUS": 3,
        "PROTOSS_GATEWAY": 1,
        "PROTOSS_CYBERNETICSCORE": 1,
        "PROTOSS_PYLON": 9,
        "PROTOSS_ASSIMILATOR": 6
      },
      "SelfBaseData": {
        "BaseCount": 1,
        "WorkerCount": 22,
        "OpenGeyserCount": 2,
        "BuiltGeyserCount": 0,
        "MinedGas": 0,
        "MineralPatchCount": 4,
        "MinedMinerals": 9775
      },
      "EnemyBaseData": {
        "BaseCount": 3,
        "WorkerCount": 16,
        "OpenGeyserCount": 0,
        "BuiltGeyserCount": 6,
        "MinedGas": 10140,
        "MineralPatchCount": 24,
        "MinedMinerals": 32400
      }
    },
    "18816": {
      "BuildHistory": {
        "0": "OneBaseCarriers"
      },
      "EnemyStrategyHistory": {},
      "ActiveEnemyStrategies": [],
      "DetectedEnemyStrategies": [],
      "SelfUnitCounts": {
        "PROTOSS_PYLON": 6,
        "PROTOSS_ASSIMILATOR": 2,
        "PROTOSS_PROBE": 22,
        "PROTOSS_SENTRY": 1,
        "PROTOSS_STARGATE": 1,
        "PROTOSS_INTERCEPTOR": 24,
        "PROTOSS_CYBERNETICSCORE": 1,
        "PROTOSS_CARRIER": 3,
        "PROTOSS_PHOTONCANNON": 5,
        "PROTOSS_SHIELDBATTERY": 6,
        "PROTOSS_GATEWAY": 1,
        "PROTOSS_NEXUS": 1,
        "PROTOSS_FLEETBEACON": 1,
        "PROTOSS_FORGE": 1
      },
      "EnemyUnitCounts": {
        "PROTOSS_STARGATE": 3,
        "PROTOSS_PROBE": 6,
        "PROTOSS_ASSIMILATOR": 8,
        "PROTOSS_PYLON": 8,
        "PROTOSS_GATEWAY": 1,
        "PROTOSS_NEXUS": 3,
        "PROTOSS_CYBERNETICSCORE": 1
      },
      "SelfBaseData": {
        "BaseCount": 1,
        "WorkerCount": 22,
        "OpenGeyserCount": 2,
        "BuiltGeyserCount": 0,
        "MinedGas": 0,
        "MineralPatchCount": 4,
        "MinedMinerals": 10280
      },
      "EnemyBaseData": {
        "BaseCount": 3,
        "WorkerCount": 6,
        "OpenGeyserCount": 0,
        "BuiltGeyserCount": 6,
        "MinedGas": 9804,
        "MineralPatchCount": 24,
        "MinedMinerals": 32400
      }
    },
    "20160": {
      "BuildHistory": {
        "0": "OneBaseCarriers"
      },
      "EnemyStrategyHistory": {},
      "ActiveEnemyStrategies": [],
      "DetectedEnemyStrategies": [],
      "SelfUnitCounts": {
        "PROTOSS_PYLON": 7,
        "PROTOSS_ASSIMILATOR": 2,
        "PROTOSS_PROBE": 22,
        "PROTOSS_SENTRY": 1,
        "PROTOSS_STARGATE": 1,
        "PROTOSS_INTERCEPTOR": 24,
        "PROTOSS_CYBERNETICSCORE": 1,
        "PROTOSS_CARRIER": 4,
        "PROTOSS_PHOTONCANNON": 5,
        "PROTOSS_SHIELDBATTERY": 6,
        "PROTOSS_GATEWAY": 1,
        "PROTOSS_NEXUS": 1,
        "PROTOSS_FLEETBEACON": 1,
        "PROTOSS_FORGE": 1
      },
      "EnemyUnitCounts": {
        "PROTOSS_STARGATE": 3,
        "PROTOSS_VOIDRAY": 4,
        "PROTOSS_ASSIMILATOR": 6,
        "PROTOSS_GATEWAY": 1,
        "PROTOSS_NEXUS": 3,
        "PROTOSS_CYBERNETICSCORE": 1,
        "PROTOSS_PYLON": 8,
        "PROTOSS_PROBE": 1
      },
      "SelfBaseData": {
        "BaseCount": 1,
        "WorkerCount": 22,
        "OpenGeyserCount": 2,
        "BuiltGeyserCount": 0,
        "MinedGas": 0,
        "MineralPatchCount": 2,
        "MinedMinerals": 10700
      },
      "EnemyBaseData": {
        "BaseCount": 3,
        "WorkerCount": 1,
        "OpenGeyserCount": 0,
        "BuiltGeyserCount": 6,
        "MinedGas": 8272,
        "MineralPatchCount": 24,
        "MinedMinerals": 32400
      }
    },
    "21504": {
      "BuildHistory": {
        "0": "OneBaseCarriers"
      },
      "EnemyStrategyHistory": {},
      "ActiveEnemyStrategies": [],
      "DetectedEnemyStrategies": [],
      "SelfUnitCounts": {
        "PROTOSS_PYLON": 7,
        "PROTOSS_ASSIMILATOR": 2,
        "PROTOSS_PROBE": 22,
        "PROTOSS_SENTRY": 1,
        "PROTOSS_STARGATE": 1,
        "PROTOSS_INTERCEPTOR": 32,
        "PROTOSS_CYBERNETICSCORE": 1,
        "PROTOSS_CARRIER": 4,
        "PROTOSS_PHOTONCANNON": 5,
        "PROTOSS_SHIELDBATTERY": 6,
        "PROTOSS_GATEWAY": 1,
        "PROTOSS_MOTHERSHIP": 1,
        "PROTOSS_NEXUS": 1,
        "PROTOSS_FLEETBEACON": 1,
        "PROTOSS_FORGE": 1
      },
      "EnemyUnitCounts": {
        "PROTOSS_STARGATE": 3,
        "PROTOSS_ASSIMILATOR": 6,
        "PROTOSS_PYLON": 5,
        "PROTOSS_CYBERNETICSCORE": 1,
        "PROTOSS_NEXUS": 4,
        "PROTOSS_VOIDRAY": 1,
        "PROTOSS_GATEWAY": 1
      },
      "SelfBaseData": {
        "BaseCount": 1,
        "WorkerCount": 22,
        "OpenGeyserCount": 2,
        "BuiltGeyserCount": 0,
        "MinedGas": 0,
        "MineralPatchCount": 0,
        "MinedMinerals": 10800
      },
      "EnemyBaseData": {
        "BaseCount": 4,
        "WorkerCount": 0,
        "OpenGeyserCount": 2,
        "BuiltGeyserCount": 6,
        "MinedGas": 9808,
        "MineralPatchCount": 32,
        "MinedMinerals": 43200
      }
    },
    "22848": {
      "BuildHistory": {
        "0": "OneBaseCarriers"
      },
      "EnemyStrategyHistory": {},
      "ActiveEnemyStrategies": [],
      "DetectedEnemyStrategies": [],
      "SelfUnitCounts": {
        "PROTOSS_PYLON": 7,
        "PROTOSS_ASSIMILATOR": 2,
        "PROTOSS_PROBE": 22,
        "PROTOSS_SENTRY": 1,
        "PROTOSS_STARGATE": 1,
        "PROTOSS_INTERCEPTOR": 32,
        "PROTOSS_CYBERNETICSCORE": 1,
        "PROTOSS_CARRIER": 4,
        "PROTOSS_PHOTONCANNON": 5,
        "PROTOSS_SHIELDBATTERY": 6,
        "PROTOSS_GATEWAY": 1,
        "PROTOSS_MOTHERSHIP": 1,
        "PROTOSS_NEXUS": 1,
        "PROTOSS_FLEETBEACON": 1,
        "PROTOSS_FORGE": 1
      },
      "EnemyUnitCounts": {
        "PROTOSS_ASSIMILATOR": 6,
        "PROTOSS_NEXUS": 3,
        "PROTOSS_VOIDRAY": 2,
        "PROTOSS_STARGATE": 2,
        "PROTOSS_GATEWAY": 1
      },
      "SelfBaseData": {
        "BaseCount": 1,
        "WorkerCount": 22,
        "OpenGeyserCount": 2,
        "BuiltGeyserCount": 0,
        "MinedGas": 0,
        "MineralPatchCount": 0,
        "MinedMinerals": 10800
      },
      "EnemyBaseData": {
        "BaseCount": 3,
        "WorkerCount": 0,
        "OpenGeyserCount": 0,
        "BuiltGeyserCount": 6,
        "MinedGas": 11890,
        "MineralPatchCount": 24,
        "MinedMinerals": 32400
      }
    },
    "24192": {
      "BuildHistory": {
        "0": "OneBaseCarriers"
      },
      "EnemyStrategyHistory": {},
      "ActiveEnemyStrategies": [],
      "DetectedEnemyStrategies": [],
      "SelfUnitCounts": {
        "PROTOSS_PYLON": 7,
        "PROTOSS_ASSIMILATOR": 2,
        "PROTOSS_PROBE": 22,
        "PROTOSS_SENTRY": 1,
        "PROTOSS_STARGATE": 1,
        "PROTOSS_INTERCEPTOR": 15,
        "PROTOSS_CYBERNETICSCORE": 1,
        "PROTOSS_CARRIER": 4,
        "PROTOSS_PHOTONCANNON": 5,
        "PROTOSS_SHIELDBATTERY": 6,
        "PROTOSS_GATEWAY": 1,
        "PROTOSS_MOTHERSHIP": 1,
        "PROTOSS_NEXUS": 1,
        "PROTOSS_FLEETBEACON": 1,
        "PROTOSS_FORGE": 1
      },
      "EnemyUnitCounts": {
        "PROTOSS_VOIDRAY": 2,
        "PROTOSS_NEXUS": 1,
        "PROTOSS_ASSIMILATOR": 2
      },
      "SelfBaseData": {
        "BaseCount": 1,
        "WorkerCount": 22,
        "OpenGeyserCount": 2,
        "BuiltGeyserCount": 0,
        "MinedGas": 0,
        "MineralPatchCount": 0,
        "MinedMinerals": 10800
      },
      "EnemyBaseData": {
        "BaseCount": 1,
        "WorkerCount": 0,
        "OpenGeyserCount": 0,
        "BuiltGeyserCount": 2,
        "MinedGas": 2858,
        "MineralPatchCount": 8,
        "MinedMinerals": 10800
      }
    },
    "25536": {
      "BuildHistory": {
        "0": "OneBaseCarriers"
      },
      "EnemyStrategyHistory": {},
      "ActiveEnemyStrategies": [],
      "DetectedEnemyStrategies": [],
      "SelfUnitCounts": {
        "PROTOSS_PYLON": 7,
        "PROTOSS_ASSIMILATOR": 2,
        "PROTOSS_PROBE": 22,
        "PROTOSS_SENTRY": 1,
        "PROTOSS_STARGATE": 1,
        "PROTOSS_INTERCEPTOR": 8,
        "PROTOSS_CYBERNETICSCORE": 1,
        "PROTOSS_CARRIER": 5,
        "PROTOSS_PHOTONCANNON": 5,
        "PROTOSS_SHIELDBATTERY": 6,
        "PROTOSS_GATEWAY": 1,
        "PROTOSS_MOTHERSHIP": 1,
        "PROTOSS_NEXUS": 1,
        "PROTOSS_FLEETBEACON": 1,
        "PROTOSS_FORGE": 1
      },
      "EnemyUnitCounts": {
        "PROTOSS_VOIDRAY": 2,
        "PROTOSS_NEXUS": 1,
        "PROTOSS_ASSIMILATOR": 1
      },
      "SelfBaseData": {
        "BaseCount": 1,
        "WorkerCount": 22,
        "OpenGeyserCount": 2,
        "BuiltGeyserCount": 0,
        "MinedGas": 0,
        "MineralPatchCount": 0,
        "MinedMinerals": 10800
      },
      "EnemyBaseData": {
        "BaseCount": 1,
        "WorkerCount": 0,
        "OpenGeyserCount": 1,
        "BuiltGeyserCount": 1,
        "MinedGas": 0,
        "MineralPatchCount": 8,
        "MinedMinerals": 10800
      }
    },
    "26880": {
      "BuildHistory": {
        "0": "OneBaseCarriers"
      },
      "EnemyStrategyHistory": {},
      "ActiveEnemyStrategies": [],
      "DetectedEnemyStrategies": [],
      "SelfUnitCounts": {
        "PROTOSS_PYLON": 7,
        "PROTOSS_ASSIMILATOR": 2,
        "PROTOSS_PROBE": 22,
        "PROTOSS_SENTRY": 1,
        "PROTOSS_STARGATE": 1,
        "PROTOSS_INTERCEPTOR": 8,
        "PROTOSS_CYBERNETICSCORE": 1,
        "PROTOSS_CARRIER": 5,
        "PROTOSS_PHOTONCANNON": 5,
        "PROTOSS_SHIELDBATTERY": 6,
        "PROTOSS_GATEWAY": 1,
        "PROTOSS_MOTHERSHIP": 1,
        "PROTOSS_NEXUS": 1,
        "PROTOSS_FLEETBEACON": 1,
        "PROTOSS_FORGE": 1
      },
      "EnemyUnitCounts": {
        "PROTOSS_VOIDRAY": 1,
        "PROTOSS_NEXUS": 2
      },
      "SelfBaseData": {
        "BaseCount": 1,
        "WorkerCount": 22,
        "OpenGeyserCount": 2,
        "BuiltGeyserCount": 0,
        "MinedGas": 0,
        "MineralPatchCount": 0,
        "MinedMinerals": 10800
      },
      "EnemyBaseData": {
        "BaseCount": 2,
        "WorkerCount": 0,
        "OpenGeyserCount": 4,
        "BuiltGeyserCount": 0,
        "MinedGas": 0,
        "MineralPatchCount": 16,
        "MinedMinerals": 21600
      }
    }
  }
}